<annotation><filename>minion_10.jpg</filename><folder>users/sibylhe//minion</folder><source><submittedBy>Sibyl He</submittedBy></source><imagesize><nrows>329</nrows><ncols>550</ncols></imagesize><object><name>minion</name><deleted>0</deleted><verified>0</verified><occluded>yes</occluded><attributes>back</attributes><parts><hasparts></hasparts><ispartof></ispartof></parts><date>20-Nov-2018 04:37:21</date><id>0</id><segm><username>anonymous</username><box><xmin>150</xmin><ymin>126</ymin><xmax>224</xmax><ymax>293</ymax></box><mask>minion_10_mask_0.png</mask><scribbles><xmin>140.75</xmin><ymin>92</ymin><xmax>238.25</xmax><ymax>314</ymax><scribble_name>minion_10_scribble_0.png</scribble_name></scribbles></segm></object><object><name>minion</name><deleted>0</deleted><verified>0</verified><occluded>yes</occluded><attributes>back</attributes><parts><hasparts></hasparts><ispartof></ispartof></parts><date>20-Nov-2018 04:37:55</date><id>1</id><segm><username>anonymous</username><box><xmin>236</xmin><ymin>193</ymin><xmax>307</xmax><ymax>292</ymax></box><mask>minion_10_mask_1.png</mask><scribbles><xmin>228.75</xmin><ymin>175.75</ymin><xmax>320.25</xmax><ymax>309.25</ymax><scribble_name>minion_10_scribble_1.png</scribble_name></scribbles></segm></object><object><name>minion</name><deleted>0</deleted><verified>0</verified><occluded>yes</occluded><attributes>back</attributes><parts><hasparts></hasparts><ispartof></ispartof></parts><date>20-Nov-2018 04:38:51</date><id>2</id><segm><username>anonymous</username><box><xmin>300</xmin><ymin>177</ymin><xmax>391</xmax><ymax>292</ymax></box><mask>minion_10_mask_2.png</mask><scribbles><xmin>293.75</xmin><ymin>154.25</ymin><xmax>409.25</xmax><ymax>314.75</ymax><scribble_name>minion_10_scribble_2.png</scribble_name></scribbles></segm></object></annotation>